MANIFEST.in
README.md
setup.cfg
setup.py
bravia_tv/__init__.py
bravia_tv/braviarc.py
bravia_tv_koying.egg-info/PKG-INFO
bravia_tv_koying.egg-info/SOURCES.txt
bravia_tv_koying.egg-info/dependency_links.txt
bravia_tv_koying.egg-info/top_level.txt