Metadata-Version: 2.1
Name: bravia-tv-koying
Version: 1.0.1
Summary: Python Bravia TV remote control
Home-page: https://github.com/dcnielsen90/python-bravia-tv.git
Maintainer: David Nielsen
Maintainer-email: dncielsen90@gmail.com
License: UNKNOWN
Platform: UNKNOWN
Classifier: Programming Language :: Python :: 3
Classifier: License :: OSI Approved :: MIT License
Classifier: Operating System :: OS Independent
Requires-Python: >=3.6
